refactorai/__init__.py
refactorai/main.py
refactorai/ai/__init__.py
refactorai/ai/ai_client.py
refactorai/ai/prompts.py
refactorai/config/__init__.py
refactorai/config/globals.py
refactorai/core/__init__.py
refactorai/core/refactor.py
refactorai/core/starts.py
refactorai/helpers/__init__.py
refactorai/helpers/functions.py
refactorai/logger/__init__.py
refactorai/logger/logger.py
refactorai-0.2.0.dist-info/licenses/LICENSE
refactorai-0.2.0.dist-info/METADATA
refactorai-0.2.0.dist-info/WHEEL
refactorai-0.2.0.dist-info/entry_points.txt
refactorai-0.2.0.dist-info/top_level.txt
refactorai-0.2.0.dist-info/RECORD
